complex_sqrt_package/__init__.py
complex_sqrt_package/sqrt_module.py
complex_sqrt_package-0.1.0.dist-info/METADATA
complex_sqrt_package-0.1.0.dist-info/WHEEL
complex_sqrt_package-0.1.0.dist-info/top_level.txt
complex_sqrt_package-0.1.0.dist-info/RECORD
